_lovely_tensors_hook.pth
_lovely_tensors_hook.py
lovely_tensors/__init__.py
lovely_tensors/_modidx.py
lovely_tensors/patch.py
lovely_tensors/repr_chans.py
lovely_tensors/repr_plt.py
lovely_tensors/repr_rgb.py
lovely_tensors/repr_str.py
lovely_tensors/utils/__init__.py
lovely_tensors/utils/config.py
lovely_tensors/utils/misc.py
lovely_tensors-0.1.21.dist-info/licenses/LICENSE
lovely_tensors-0.1.21.dist-info/METADATA
lovely_tensors-0.1.21.dist-info/WHEEL
lovely_tensors-0.1.21.dist-info/entry_points.txt
lovely_tensors-0.1.21.dist-info/top_level.txt
lovely_tensors-0.1.21.dist-info/RECORD
