Metadata-Version: 2.4
Name: lovely-tensors
Version: 0.1.21
Summary: ❤️ Lovely Tensors
Home-page: https://github.com/xl0/lovely-tensors
Author: Alexey Zaytsev
Author-email: alexey.zaytsev@gmail.com
License: MIT License
Keywords: jupyter pytorch tensor visualisation
Classifier: Development Status :: 4 - Beta
Classifier: Intended Audience :: Developers
Classifier: Natural Language :: English
Classifier: Programming Language :: Python :: 3.7
Classifier: Programming Language :: Python :: 3.8
Classifier: Programming Language :: Python :: 3.9
Classifier: Programming Language :: Python :: 3.10
Classifier: License :: OSI Approved :: MIT License
Requires-Python: >=3.7
License-File: LICENSE
Requires-Dist: torch
Requires-Dist: lovely-numpy>=0.2.18
Provides-Extra: dev
Requires-Dist: nbdev; extra == "dev"
Requires-Dist: twine; extra == "dev"
Requires-Dist: setuptools; extra == "dev"
Dynamic: author
Dynamic: author-email
Dynamic: classifier
Dynamic: description
Dynamic: description-content-type
Dynamic: home-page
Dynamic: keywords
Dynamic: license
Dynamic: license-file
Dynamic: provides-extra
Dynamic: requires-dist
Dynamic: requires-python
Dynamic: summary
